setup.py
NoraCalculator/__init__.py
NoraCalculator/calculator.py
NoraCalculator/python_code.py
NoraCalculator/test.py
NoraCalculator.egg-info/PKG-INFO
NoraCalculator.egg-info/SOURCES.txt
NoraCalculator.egg-info/dependency_links.txt
NoraCalculator.egg-info/not-zip-safe
NoraCalculator.egg-info/top_level.txt