Metadata-Version: 1.0
Name: NoraCalculator
Version: 0.0.1
Summary: An example package PyPi using math functions.
Home-page: https://github.com/wjnnora/SamplePyPi
Author: Wellington Nora
Author-email: wellington_nora94@hotmail.com
License: UNKNOWN
Platform: UNKNOWN
